dmhylib/DmhySearch.py
dmhylib/__init__.py
dmhylib/byte_convert.py
dmhylib/cli.py
dmhylib/url_get.py
Dmhylib-2.0.0.dist-info/LICENCE
Dmhylib-2.0.0.dist-info/METADATA
Dmhylib-2.0.0.dist-info/WHEEL
Dmhylib-2.0.0.dist-info/entry_points.txt
Dmhylib-2.0.0.dist-info/top_level.txt
Dmhylib-2.0.0.dist-info/RECORD
